django_pdfgen-1.2.3.dist-info/DESCRIPTION.rst
django_pdfgen-1.2.3.dist-info/METADATA
django_pdfgen-1.2.3.dist-info/RECORD
django_pdfgen-1.2.3.dist-info/WHEEL
django_pdfgen-1.2.3.dist-info/metadata.json
django_pdfgen-1.2.3.dist-info/top_level.txt
pdfgen/__init__.py
pdfgen/barcode.py
pdfgen/decorators.py
pdfgen/flowables.py
pdfgen/parser.py
pdfgen/shortcuts.py
pdfgen/management/__init__.py
pdfgen/management/commands/__init__.py
pdfgen/management/commands/make_pdf.py
