Metadata-Version: 2.0
Name: django-pdfgen
Version: 1.2.3
Summary: Generation of PDF documents
Home-page: https://github.com/vikingco/django-pdfgen
Author: Jef Geskens, Unleashed NV
Author-email: operations@unleashed.be
License: BSD
Platform: UNKNOWN
Classifier: Intended Audience :: Developers
Classifier: Programming Language :: Python
Classifier: Operating System :: OS Independent
Classifier: Environment :: Web Environment
Classifier: Framework :: Django
Requires-Dist: reportlab (>=3.2.0)
